rcrlm/__init__.py
rcrlm/evals.py
rcrlm/main.py
rcrlm/qwen3.py
rcrlm/utils.py
rcrlm-0.0.2.dist-info/licenses/LICENSE
rcrlm-0.0.2.dist-info/METADATA
rcrlm-0.0.2.dist-info/WHEEL
rcrlm-0.0.2.dist-info/entry_points.txt
rcrlm-0.0.2.dist-info/top_level.txt
rcrlm-0.0.2.dist-info/RECORD
