Metadata-Version: 2.4
Name: rcrlm
Version: 0.0.2
Summary: rcr-lm: Collapse layers into a recurrent block
Home-page: https://github.com/JosefAlbers/rcrlm
Author: J Joe
Author-email: albersj66@gmail.com
License: Apache-2.0
License-File: LICENSE
Requires-Dist: mlx==0.30.0; platform_system == "Darwin"
Requires-Dist: tokenizerz==0.0.3a4
Requires-Dist: tqdm
Requires-Dist: datasets
Provides-Extra: cuda
Requires-Dist: mlx[cuda]; extra == "cuda"
Provides-Extra: cpu
Requires-Dist: mlx[cpu]; extra == "cpu"
Provides-Extra: no-mlx
Dynamic: author
Dynamic: author-email
Dynamic: description
Dynamic: description-content-type
Dynamic: home-page
Dynamic: license
Dynamic: license-file
Dynamic: provides-extra
Dynamic: requires-dist
Dynamic: summary
